Metadata-Version: 2.1
Name: Kanitham
Version: 0.0.1
Summary: Simple Mathematical Operations
Author: Ariharasudhan
